soium/__init__.py
soium/base_page.py
soium/demo.py
soium/page_objects.py
soium/setup.py
soium/common/__init__.py
soium/common/locator.py
soium/plugins/__init__.py
soium/plugins/py_test_info.py
soium/support/__init__.py
soium/support/constants.py
soium/support/expected_conditions.py
soium/support/proxy_config.py
soium/support/reverse_address.py
soium/support/util.py
soium/support/wait.py
soium/webdriver/__init__.py
soium/webdriver/appium/__init__.py
soium/webdriver/appium/profile.py
soium/webdriver/appium/webdriver.py
soium/webdriver/selenium/__init__.py
soium/webdriver/selenium/profile.py
soium/webdriver/selenium/webdriver.py
swim/__init__.py
swim/main.py
swim/setup.py
swim/commons/__init__.py
swim/commons/locator.py
swim/drivers/__init__.py
swim/drivers/android/__init__.py
swim/drivers/android/android_driver.py
swim/drivers/browser/__init__.py
swim/drivers/browser/browser_driver.py
swim/drivers/ios/__init__.py
swim/drivers/ios/ios_driver.py
swim/drivers/ios/usb_driver.py
swim/pages/__init__.py
swim/pages/element_page.py
swim/pages/object_page.py
swim/plugins/__init__.py
swim/plugins/pytest_plugins.py
swim/utils/__init__.py
swim/utils/abt_util.py
swim/utils/clean_util.py
swim/utils/ios_shell.py
swim/utils/language_util.py
swim/utils/log_util.py
swim/utils/shell_ios_util.py
swim/utils/upload_util.py
testium-1.25.47.dist-info/METADATA
testium-1.25.47.dist-info/WHEEL
testium-1.25.47.dist-info/top_level.txt
testium-1.25.47.dist-info/RECORD
